<?xml version="1.0" encoding="utf-8" ?><dwsync><file name="courier.php" server="ftp.tabascoweb.com" local="3441160800" remote="20621029984" /><file name="helvetica.php" server="ftp.tabascoweb.com" local="3441160800" remote="20621029984" /><file name="helveticab.php" server="ftp.tabascoweb.com" local="3441160800" remote="20621029984" /><file name="helveticabi.php" server="ftp.tabascoweb.com" local="3441160800" remote="20621029984" /><file name="helveticai.php" server="ftp.tabascoweb.com" local="3441160800" remote="20621029984" /><file name="index.html" server="ftp.tabascoweb.com" local="3443933460" remote="20623802644" /><file name="symbol.php" server="ftp.tabascoweb.com" local="3441160800" remote="20621029984" /><file name="times.php" server="ftp.tabascoweb.com" local="3441160800" remote="20621029984" /><file name="timesb.php" server="ftp.tabascoweb.com" local="3441160800" remote="20621029984" /><file name="timesbi.php" server="ftp.tabascoweb.com" local="3441160800" remote="20621029984" /><file name="timesi.php" server="ftp.tabascoweb.com" local="3441160800" remote="20621029984" /><file name="zapfdingbats.php" server="ftp.tabascoweb.com" local="3441160800" remote="20621029984" /></dwsync>